smartzoom/__init__.py
smartzoom/main.py
smartzoom-0.1.0.dist-info/licenses/LICENSE
smartzoom-0.1.0.dist-info/METADATA
smartzoom-0.1.0.dist-info/WHEEL
smartzoom-0.1.0.dist-info/entry_points.txt
smartzoom-0.1.0.dist-info/top_level.txt
smartzoom-0.1.0.dist-info/RECORD
