Metadata-Version: 2.4
Name: smartzoom
Version: 0.1.0
Summary: A Python utility to automatically apply a smooth, continuous zoom to a video, perfectly framing its content.
Home-page: https://github.com/AMAMazing/smartzoom
Author: Alex M
Author-email: alexmalone489@gmail.com
Keywords: video,zoom,automation,opencv,ffmpeg,cli
Classifier: Programming Language :: Python :: 3
Classifier: License :: OSI Approved :: MIT License
Classifier: Operating System :: OS Independent
Classifier: Development Status :: 4 - Beta
Classifier: Intended Audience :: Developers
Classifier: Topic :: Multimedia :: Video
Requires-Python: >=3.6
License-File: LICENSE
Requires-Dist: opencv-python
Requires-Dist: numpy
Dynamic: author
Dynamic: author-email
Dynamic: classifier
Dynamic: description
Dynamic: description-content-type
Dynamic: home-page
Dynamic: keywords
Dynamic: license-file
Dynamic: requires-dist
Dynamic: requires-python
Dynamic: summary
